hns_chargebee_api/__init__.py
hns_chargebee_api-21.11.1.dist-info/LICENSE
hns_chargebee_api-21.11.1.dist-info/METADATA
hns_chargebee_api-21.11.1.dist-info/WHEEL
hns_chargebee_api-21.11.1.dist-info/top_level.txt
hns_chargebee_api-21.11.1.dist-info/RECORD
